server.py
mcp_local_image_reader-0.1.1.dist-info/METADATA
mcp_local_image_reader-0.1.1.dist-info/WHEEL
mcp_local_image_reader-0.1.1.dist-info/entry_points.txt
mcp_local_image_reader-0.1.1.dist-info/licenses/LICENSE
mcp_local_image_reader-0.1.1.dist-info/RECORD
