Metadata-Version: 2.4
Name: mcp-local-image-reader
Version: 0.1.1
Summary: A simple MCP server that reads local images and returns them as ImageContent for LLM vision analysis
Project-URL: Homepage, https://github.com/masachika-kamada/mcp-local-image-reader
Project-URL: Repository, https://github.com/masachika-kamada/mcp-local-image-reader
Project-URL: Issues, https://github.com/masachika-kamada/mcp-local-image-reader/issues
Author: masachika-kamada
License-Expression: MIT
License-File: LICENSE
Keywords: ai,image,llm,mcp,model-context-protocol,vision
Classifier: Development Status :: 4 - Beta
Classifier: Intended Audience :: Developers
Classifier: License :: OSI Approved :: MIT License
Classifier: Programming Language :: Python :: 3
Classifier: Programming Language :: Python :: 3.11
Classifier: Programming Language :: Python :: 3.12
Classifier: Programming Language :: Python :: 3.13
Classifier: Topic :: Scientific/Engineering :: Artificial Intelligence
Requires-Python: >=3.11
Requires-Dist: mcp>=1.0.0
